imk/__init__.py
imk/__main__.py
imk-0.0.3.dist-info/LICENSE
imk-0.0.3.dist-info/METADATA
imk-0.0.3.dist-info/WHEEL
imk-0.0.3.dist-info/dependency_links.txt
imk-0.0.3.dist-info/entry_points.txt
imk-0.0.3.dist-info/top_level.txt
imk-0.0.3.dist-info/RECORD
