Metadata-Version: 2.1
Name: imk
Version: 0.0.3
Summary: A simple commandline app for building custom cli tools
Home-page: UNKNOWN
Author: Krishna Agrawal
Author-email: imkrishnaagrawal@gmail.com
License: MIT
Platform: UNKNOWN
Classifier: License :: OSI Approved :: MIT License
Classifier: Programming Language :: Python :: 2.7
Classifier: Programming Language :: Python :: 3
Classifier: Programming Language :: Python :: 3.7
Requires-Python: >=2.7
Requires-Dist: pyyaml
